formula1/__init__.py
formula1/f1.py
formula1_cli-0.2.0.dist-info/LICENSE
formula1_cli-0.2.0.dist-info/METADATA
formula1_cli-0.2.0.dist-info/WHEEL
formula1_cli-0.2.0.dist-info/entry_points.txt
formula1_cli-0.2.0.dist-info/top_level.txt
formula1_cli-0.2.0.dist-info/RECORD
