Metadata-Version: 2.1
Name: formula1-cli
Version: 0.2.0
Summary: Formula 1 Command-Line Tools
Home-page: https://github.com/halldorstefans/f1-cli
Author: Halldor Stefansson
Author-email: halldor@halldorstefans.com
License: MIT
Classifier: Programming Language :: Python :: 3.8
Classifier: License :: OSI Approved :: MIT License
License-File: LICENSE
Requires-Dist: click >=8.0
Requires-Dist: requests >=2.25
Requires-Dist: pandas >=1.2
